bolt/__init__.py
bolt/django.py
bolt/flask.py
cyberchief_bolt-0.0.18.dist-info/LICENSE
cyberchief_bolt-0.0.18.dist-info/METADATA
cyberchief_bolt-0.0.18.dist-info/WHEEL
cyberchief_bolt-0.0.18.dist-info/top_level.txt
cyberchief_bolt-0.0.18.dist-info/RECORD
