Metadata-Version: 2.1
Name: cyberchief-bolt
Version: 0.0.18
Summary: The Python Agent for cyberchief-bolt
Home-page: https://www.secure.cyberchief.ai
License: MIT
Project-URL: Documentation, https://github.com/bolttest12345/bolttest
Project-URL: Source Code, https://github.com/bolttest12345/bolttest
Classifier: Development Status :: 3 - Alpha
Classifier: Intended Audience :: Developers
Classifier: Operating System :: OS Independent
Classifier: License :: OSI Approved :: MIT License
Classifier: Programming Language :: Python :: 3
Classifier: Programming Language :: Python :: 3.4
Classifier: Programming Language :: Python :: 3.5
Classifier: Programming Language :: Python :: 3.6
Classifier: Programming Language :: Python :: 3.7
Classifier: Programming Language :: Python :: 3.8
Classifier: Programming Language :: Python :: 3.9
Requires-Python: >=3.4
License-File: LICENSE
